{"face_data": {"1": {"name": "Montserrat", "surname": "Quintero", "user_id": 21080817, "career": "Quimica", "acss": "Alumno", "data_path": "{TinyUuid}:f051972c-3106-4d1e-a568-79ff09a3a790", "created_at": "{TinyDate}:2024-05-11T23:03:37.992543"}, "2": {"name": "Daniel", "surname": "Concepcion", "user_id": 21080818, "career": "Informatica", "acss": "Alumno", "data_path": "{TinyUuid}:54f82548-47fb-4710-b741-40ceac9d28e4", "created_at": "{TinyDate}:2024-05-26T12:30:46.704742"}, "3": {"name": "Jose", "surname": "Angel", "user_id": 21080815, "worker_number": null, "career": "Electr\u00f3nica", "acss": "Alumno", "data_path": "{TinyUuid}:f86418f0-41f1-4f24-8ca6-e2f4cb8900ed", "created_at": "{TinyDate}:2024-05-30T10:27:16.809268"}, "4": {"name": "Ernesto", "surname": "Garcia", "user_id": 21080815, "worker_number": null, "career": "Inform\u00e1tica", "acss": "Alumno", "data_path": "{TinyUuid}:0991b7d2-abbe-43ee-b84e-eb42452766b3", "created_at": "{TinyDate}:2024-05-30T10:30:27.770942"}, "5": {"name": "Lisandro", "surname": "Borja", "user_id": 21080815, "worker_number": null, "career": "Inform\u00e1tica", "acss": "Alumno", "data_path": "{TinyUuid}:ad19a409-1bd2-4c8a-b471-9ffcbf812f7b", "created_at": "{TinyDate}:2024-05-30T10:33:00.984004"}, "6": {"name": "Genesis", "surname": "Lopez", "user_id": null, "worker_number": null, "career": null, "acss": "Invitado", "data_path": "{TinyUuid}:379fb265-ca5b-41a7-95c3-b2cbe77e22de", "created_at": "{TinyDate}:2024-05-30T10:33:21.734278"}, "7": {"name": "Jose Angel", "surname": "Perez", "user_id": 56885626, "worker_number": null, "career": "Mec\u00e1nica", "acss": "Alumno", "data_path": "{TinyUuid}:36e901be-d551-46c4-a1a4-1c48ff182ae8", "created_at": "{TinyDate}:2024-05-30T10:35:58.761426"}}}